odoo/addons/mgmtsystem_partner/README.rst
odoo/addons/mgmtsystem_partner/__init__.py
odoo/addons/mgmtsystem_partner/__manifest__.py
odoo/addons/mgmtsystem_partner/i18n/es.po
odoo/addons/mgmtsystem_partner/i18n/fa.po
odoo/addons/mgmtsystem_partner/i18n/it.po
odoo/addons/mgmtsystem_partner/i18n/mgmtsystem_partner.pot
odoo/addons/mgmtsystem_partner/models/__init__.py
odoo/addons/mgmtsystem_partner/models/res_partner.py
odoo/addons/mgmtsystem_partner/readme/CONTRIBUTORS.md
odoo/addons/mgmtsystem_partner/readme/DESCRIPTION.md
odoo/addons/mgmtsystem_partner/readme/HISTORY.md
odoo/addons/mgmtsystem_partner/readme/USAGE.md
odoo/addons/mgmtsystem_partner/static/description/icon.png
odoo/addons/mgmtsystem_partner/static/description/index.html
odoo_addon_mgmtsystem_partner-18.0.1.0.0.3.dist-info/METADATA
odoo_addon_mgmtsystem_partner-18.0.1.0.0.3.dist-info/WHEEL
odoo_addon_mgmtsystem_partner-18.0.1.0.0.3.dist-info/top_level.txt
odoo_addon_mgmtsystem_partner-18.0.1.0.0.3.dist-info/RECORD
